<?xml version="1.0" encoding="utf-8"?>
<optionset Name="new_activitycategory" localizedName="Activity Category">
  <OptionSetType>picklist</OptionSetType>
  <IsGlobal>1</IsGlobal>
  <IntroducedVersion>1.0</IntroducedVersion>
  <IsCustomizable>1</IsCustomizable>
  <displaynames>
    <displayname description="Activity Category" languagecode="1033" />
  </displaynames>
  <Descriptions>
    <Description description="" languagecode="1033" />
  </Descriptions>
  <options>
    <option value="100000000">
      <labels>
        <label description="SLS - Sales" languagecode="1033" />
      </labels>
      <Descriptions>
        <Description description="" languagecode="1033" />
      </Descriptions>
    </option>
    <option value="100000005">
      <labels>
        <label description="NS - Non Sales Related" languagecode="1033" />
      </labels>
      <Descriptions>
        <Description description="" languagecode="1033" />
      </Descriptions>
    </option>
    <option value="100000006">
      <labels>
        <label description="LG - Lead Generation" languagecode="1033" />
      </labels>
      <Descriptions>
        <Description description="" languagecode="1033" />
      </Descriptions>
    </option>
    <option value="100000007">
      <labels>
        <label description="SE - Sales Engineering" languagecode="1033" />
      </labels>
      <Descriptions>
        <Description description="" languagecode="1033" />
      </Descriptions>
    </option>
    <option value="100000001">
      <labels>
        <label description="Invalid Option" languagecode="1033" />
      </labels>
      <Descriptions>
        <Description description="" languagecode="1033" />
      </Descriptions>
    </option>
  </options>
</optionset>