<?xml version="1.0" encoding="utf-8"?>
<savedquery>
  <IsCustomizable>1</IsCustomizable>
  <CanBeDeleted>1</CanBeDeleted>
  <isquickfindquery>0</isquickfindquery>
  <isprivate>0</isprivate>
  <isdefault>0</isdefault>
  <returnedtypecode>4202</returnedtypecode>
  <savedqueryid>{a3b477f4-169b-e311-aa1b-6c3be5a84d70}</savedqueryid>
  <layoutxml>
    <grid name="resultset" object="4202" jump="subject" select="1" preview="1" icon="1">
      <row name="result" id="activityid">
        <cell name="subject" width="300" />
        <cell name="from" width="100" disableSorting="1" />
        <cell name="to" width="100" disableSorting="1" />
        <cell name="cc" width="100" disableSorting="1" />
        <cell name="regardingobjectid" width="100" />
        <cell name="prioritycode" width="100" />
        <cell name="statuscode" width="100" />
        <cell name="modifiedon" width="100" />
      </row>
    </grid>
  </layoutxml>
  <querytype>0</querytype>
  <fetchxml>
    <fetch version="1.0" output-format="xml-platform" mapping="logical">
      <entity name="email">
        <order attribute="modifiedon" descending="true" />
        <attribute name="to" />
        <attribute name="regardingobjectid" />
        <attribute name="prioritycode" />
        <attribute name="modifiedon" />
        <attribute name="from" />
        <attribute name="cc" />
        <attribute name="statuscode" />
        <attribute name="activityid" />
      </entity>
    </fetch>
  </fetchxml>
  <IntroducedVersion>1.0</IntroducedVersion>
  <LocalizedNames>
    <LocalizedName description="Emails Regarding" languagecode="1033" />
  </LocalizedNames>
</savedquery>